tree_sitter_regex/__init__.py
tree_sitter_regex/__init__.pyi
tree_sitter_regex/_binding.abi3.so
tree_sitter_regex/binding.c
tree_sitter_regex/py.typed
tree_sitter_regex/queries/highlights.scm
tree_sitter_regex-0.25.0.dist-info/METADATA
tree_sitter_regex-0.25.0.dist-info/WHEEL
tree_sitter_regex-0.25.0.dist-info/top_level.txt
tree_sitter_regex-0.25.0.dist-info/RECORD
tree_sitter_regex-0.25.0.dist-info/licenses/LICENSE
